diabetes_model/__init__.py
diabetes_model/pipeline.py
diabetes_model/predict.py
diabetes_model/train.py
diabetes_model_dl-0.1.0.dist-info/licenses/LICENSE
diabetes_model_dl-0.1.0.dist-info/METADATA
diabetes_model_dl-0.1.0.dist-info/WHEEL
diabetes_model_dl-0.1.0.dist-info/top_level.txt
diabetes_model_dl-0.1.0.dist-info/RECORD
