Metadata-Version: 2.4
Name: diabetes-model-dl
Version: 0.1.0
Summary: Modelo de regresion logistica para clasificacion de diabetes
Author: Diego Lemus
License: MIT
Classifier: Programming Language :: Python :: 3
Classifier: License :: OSI Approved :: MIT License
Classifier: Operating System :: OS Independent
Requires-Python: >=3.8
License-File: LICENSE
Requires-Dist: pandas
Requires-Dist: scikit-learn
Requires-Dist: joblib
Dynamic: license-file
